mutechromecastads.py
mutechromecastads-0.1.1.dist-info/METADATA
mutechromecastads-0.1.1.dist-info/WHEEL
mutechromecastads-0.1.1.dist-info/entry_points.txt
mutechromecastads-0.1.1.dist-info/RECORD
