Metadata-Version: 2.1
Name: mutechromecastads
Version: 0.1.1
Summary: 
Author: rikyiso01
Author-email: riky.isola@gmail.com
Requires-Python: >=3.10,<4.0
Classifier: Programming Language :: Python :: 3
Classifier: Programming Language :: Python :: 3.10
Classifier: Programming Language :: Python :: 3.11
Classifier: Programming Language :: Python :: 3.12
Requires-Dist: PyChromecast (==9.4.0)
Requires-Dist: protobuf (==3.20.3)
